data/__init__.py
data/input/__init__.py
data/output/__init__.py
data/shapefiles/__init__.py
plaguepy/__init__.py
plaguepy/bereken.py
plaguepy/convertCSV.py
plaguepy/plot/__init__.py
plaguepy/plot/norm_verd.py
plaguepy/plot/plot.py
test/__init__.py
test/test_bereken.py
plaguepy-2020.4.12.1.dist-info/LICENSE
plaguepy-2020.4.12.1.dist-info/METADATA
plaguepy-2020.4.12.1.dist-info/WHEEL
plaguepy-2020.4.12.1.dist-info/top_level.txt
plaguepy-2020.4.12.1.dist-info/RECORD
