Metadata-Version: 2.1
Name: plaguepy
Version: 2020.4.12.1
Summary: Ziekteverspreiding gevisualiseerd
Home-page: https://github.com/denbergvanthijs/plaguepy
Author: Thijs van den Berg
Author-email: denbergvanthijs@gmail.com
License: UNKNOWN
Platform: UNKNOWN
Classifier: Programming Language :: Python :: 3
Classifier: License :: OSI Approved :: Apache Software License
Classifier: Operating System :: OS Independent
